MANIFEST.in
README.md
readme.md
setup.py
bin/gen_names_dbialk.bat
get_names_db/__init__.py
get_names_db/gen_names_dbialk.py
my_cool_lib_dbialk.egg-info/PKG-INFO
my_cool_lib_dbialk.egg-info/SOURCES.txt
my_cool_lib_dbialk.egg-info/dependency_links.txt
my_cool_lib_dbialk.egg-info/requires.txt
my_cool_lib_dbialk.egg-info/top_level.txt