Metadata-Version: 1.0
Name: my-cool-lib-dbialk
Version: 1.0.4
Summary: Super useful library
Home-page: https://github.com/
Author: Dawid Bialk
Author-email: dev@example.com
License: UNKNOWN
Platform: UNKNOWN
